singleton_decorator1/__init__.py
singleton_decorator1/_version.py
singleton_decorator1/py.typed
singleton_decorator1/singleton.py
singleton_decorator1-1.0.2.dist-info/METADATA
singleton_decorator1-1.0.2.dist-info/WHEEL
singleton_decorator1-1.0.2.dist-info/licenses/LICENSE.md
singleton_decorator1-1.0.2.dist-info/RECORD
