Metadata-Version: 2.4
Name: singleton-decorator1
Version: 1.0.2
Summary: Singleton decorator which is: thread-safe, copy safe, mypy compliant, not wrapped class
Project-URL: repository, https://codeberg.org/Sojournings/singleton-decorator.git
Project-URL: issues, https://codeberg.org/Sojournings/singleton-decorator/issues
Author: Editor 82 of wiki.python.org
Author-email: Doug Sojourner <doug@sojournings.org>
License: GNU General Public License v3 (GPLv3)
License-File: LICENSE.md
Keywords: copy safe,decorator,singleton,testable,threadsafe,typed,verified
Classifier: Development Status :: 5 - Production/Stable
Classifier: Intended Audience :: Developers
Classifier: License :: OSI Approved :: GNU General Public License v3 (GPLv3)
Classifier: Natural Language :: English
Classifier: Operating System :: OS Independent
Classifier: Programming Language :: Python :: 3
Classifier: Programming Language :: Python :: 3 :: Only
Classifier: Programming Language :: Python :: 3.7
Classifier: Programming Language :: Python :: 3.8
Classifier: Programming Language :: Python :: 3.9
Classifier: Programming Language :: Python :: 3.10
Classifier: Programming Language :: Python :: 3.11
Classifier: Programming Language :: Python :: 3.12
Classifier: Programming Language :: Python :: 3.13
Classifier: Topic :: Software Development
Classifier: Topic :: Software Development :: Libraries
Classifier: Topic :: Software Development :: Libraries :: Python Modules
Classifier: Typing :: Typed
Requires-Python: <4.0,>=3.7
Requires-Dist: project-version-finder>=0.3.0
